pysuite/__init__.py
pysuite/auth.py
pysuite/drive.py
pysuite/gmail.py
pysuite/sheets.py
pysuite/storage.py
pysuite/utilities.py
pysuite/vision.py
pysuite-0.4.0.dist-info/LICENSE
pysuite-0.4.0.dist-info/METADATA
pysuite-0.4.0.dist-info/WHEEL
pysuite-0.4.0.dist-info/top_level.txt
pysuite-0.4.0.dist-info/RECORD
