Metadata-Version: 2.1
Name: pysuite
Version: 0.4.0
Summary: A data scientist's toolbox for Google Suite Apps
Home-page: https://staftermath.github.io/pysuite/index.html
Author: Weiwen Gu
Author-email: gwengww@gmail.com
License: bsd-3-clause
Download-URL: https://github.com/staftermath/pysuite/archive/0.4.0.tar.gz
Platform: UNKNOWN
Requires-Python: >=3.6.0
Requires-Dist: google-api-python-client (>=1.7.8)
Requires-Dist: google-api-core (>=1.31.1)
Requires-Dist: google-auth (>=1.20.1)
Requires-Dist: pyparsing (<3.0.0,>=2.4.7)
Requires-Dist: google-auth-httplib2 (>=0.0.4)
Requires-Dist: google-auth-oauthlib (>=0.4.1)
Requires-Dist: googleapis-common-protos (>=1.6)
Requires-Dist: google-cloud-vision (>=2.4.2)
Requires-Dist: google-cloud-storage (>=1.42.3)
